forex_data/__init__.py
forex_data/config/__init__.py
forex_data/config/config_file.py
forex_data/data_management/__init__.py
forex_data/data_management/common.py
forex_data/data_management/database.py
forex_data/data_management/historicaldata.py
forex_data/data_management/realtimedata.py
forex_data_aggregator-0.1.4.dist-info/LICENSE
forex_data_aggregator-0.1.4.dist-info/METADATA
forex_data_aggregator-0.1.4.dist-info/WHEEL
forex_data_aggregator-0.1.4.dist-info/RECORD
