Metadata-Version: 2.3
Name: forex_data_aggregator
Version: 0.1.4
Summary: Data aggregation for forex market data
License: MIT
Author: Nicola Fiorato
Author-email: fiorato.nicola@gmail.com
Requires-Python: >=3.12,<3.13
Classifier: License :: OSI Approved :: MIT License
Classifier: Programming Language :: Python :: 3
Classifier: Programming Language :: Python :: 3.12
Requires-Dist: adbc-driver-sqlite (>=1.6.0,<2.0.0)
Requires-Dist: alpha-vantage (>=2.3.1,<3.0.0)
Requires-Dist: bs4 (>=0.0.2,<0.0.3)
Requires-Dist: connectorx (>=0.4.3,<0.5.0)
Requires-Dist: debugpy (>=1.8.5,<2.0.0)
Requires-Dist: dotty-dict (>=1.3.1,<2.0.0)
Requires-Dist: duckdb (>=1.3.1,<2.0.0)
Requires-Dist: flake8 (>=7.1.1,<8.0.0)
Requires-Dist: holidays (>=0.89,<0.90)
Requires-Dist: iteration-utilities (>=0.12.1,<0.13.0)
Requires-Dist: loguru (>=0.7.2,<0.8.0)
Requires-Dist: matplotlib (>=3.9.2)
Requires-Dist: mpl-finance (>=0.10.1,<0.11.0)
Requires-Dist: mplfinance (>=0.12.9b7,<0.13.0)
Requires-Dist: mypy (>=1.14.1,<2.0.0)
Requires-Dist: numpy (<2.0.0)
Requires-Dist: pandas (>=2.0.0)
Requires-Dist: pandas-stubs (>=2.2.3.241126,<3.0.0.0)
Requires-Dist: polars (>=0.20.7)
Requires-Dist: polygon-api-client (>=1.5.0,<2.0.0)
Requires-Dist: pyaml (>=21.10.1,<22.0.0)
Requires-Dist: pyarrow (>=14.0.2)
Requires-Dist: pyinstrument (>=5.1.2,<6.0.0)
Requires-Dist: pytest (>=8.1.1,<9.0.0)
Requires-Dist: pytest-flake8 (>=1.3.0,<2.0.0)
Requires-Dist: pytest-mypy (>=0.10.3,<0.11.0)
Requires-Dist: requests (>=2.28.1,<3.0.0)
Requires-Dist: scipy (>=1.11.4,<2.0.0)
Requires-Dist: setuptools (>=69.0.2,<70.0.0)
